{
    "ww_swisstopo_link": "../core/legends/ww_swisstopo.php",
    "ww_swisstopo_title": "Wanderwege swisstopo",

    "schweizmobil_link": "../core/legends/schweizmobil_de.htm",
    "schweizmobil_title": "SchweizMobil",
    "skatingland_etappen_link": "../core/legends/sm_skl_etappen.php",
    "skatingland_etappen_title": "SchweizMobil: Skatingland Etappen",
    "skatingland_routen_link": "../core/legends/sm_skl_routen.php",
    "skatingland_routen_title": "SchweizMobil: Skatingland Routen",
    "veloland_etappen_link": "../core/legends/sm_vl_etappen.php",
    "veloland_etappen_title": "SchweizMobil: Veloland Etappen",
    "veloland_routen_link": "../core/legends/sm_vl_routen.php",
    "veloland_routen_title": "SchweizMobil: Veloland Routen",
    "wanderland_etappen_link": "../core/legends/sm_wl_etappen.php",
    "wanderland_etappen_title": "SchweizMobil: Wanderland Etappen",
    "wanderland_routen_link": "../core/legends/sm_wl_routen.php",
    "wanderland_routen_title": "SchweizMobil: Wanderland Routen",
    "mountainbikeland_etappen_link": "../core/legends/sm_mbl_etappen.php",
    "mountainbikeland_etappen_title": "SchweizMobil: Mountainbikeland Etappen",
    "mountainbikeland_routen_link": "../core/legends/sm_mbl_routen.php",
    "mountainbikeland_routen_title": "SchweizMobil: Mountainbikeland Routen",
    
    "wintersport_title": "Wintersport",
    "wintersport_link": "../core/legends/wintersport_de.htm"
}